everytools/__init__.py
everytools/config.py
everytools/everytools.py
everytools/dll/Everything32.dll
everytools/dll/Everything64.dll
everytools-0.0.1.4.dist-info/LICENSE
everytools-0.0.1.4.dist-info/METADATA
everytools-0.0.1.4.dist-info/WHEEL
everytools-0.0.1.4.dist-info/top_level.txt
everytools-0.0.1.4.dist-info/RECORD
