Metadata-Version: 2.1
Name: everytools
Version: 0.0.1.4
Summary: python tools for everything
Home-page: https://github.com/yangjiada/everytools
Author: Jan Yang
Author-email: yang.jiada@foxmail.com
Keywords: everything,everytools,windows,file,search,file search
Requires-Python: >=3.9
License-File: LICENSE
